setup.py
pygments_style_exponent/__init__.py
pygments_style_exponent.egg-info/PKG-INFO
pygments_style_exponent.egg-info/SOURCES.txt
pygments_style_exponent.egg-info/dependency_links.txt
pygments_style_exponent.egg-info/entry_points.txt
pygments_style_exponent.egg-info/requires.txt
pygments_style_exponent.egg-info/top_level.txt