Metadata-Version: 1.1
Name: pygments-style-exponent
Version: 0.1
Summary: Pygments style for Exponent (getexponent.com)
Home-page: https://github.com/exponentjs/pygments-style-exponent
Author: Brent Vatne
Author-email: brentvatne@gmail.com
License: BSD
Platform: UNKNOWN
Classifier: Development Status :: 4 - Beta
Classifier: Environment :: Plugins
Classifier: Intended Audience :: Developers
Classifier: License :: OSI Approved :: BSD License
Classifier: Operating System :: OS Independent
Classifier: Programming Language :: Python
Classifier: Programming Language :: Python :: 2
Classifier: Programming Language :: Python :: 3
Classifier: Topic :: Software Development :: Libraries :: Python Modules
